pymongo_auth_aws/__init__.py
pymongo_auth_aws/auth.py
pymongo_auth_aws/errors.py
pymongo_auth_aws/version.py
pymongo_auth_aws-1.2.0.dist-info/METADATA
pymongo_auth_aws-1.2.0.dist-info/WHEEL
pymongo_auth_aws-1.2.0.dist-info/licenses/LICENSE
pymongo_auth_aws-1.2.0.dist-info/RECORD
