Metadata-Version: 2.3
Name: pymongo-auth-aws
Version: 1.2.0
Summary: MONGODB-AWS authentication support for PyMongo
Project-URL: Homepage, https://github.com/mongodb/pymongo-auth-aws
Author-email: Shane Harvey <drivers-python-noreply@mongodb.com>
License:                                  Apache License
License-File: LICENSE
Keywords: MONGODB-AWS,mongo,mongodb,pymongo,pymongo-auth-aws
Classifier: Development Status :: 5 - Production/Stable
Classifier: Intended Audience :: Developers
Classifier: License :: OSI Approved :: Apache Software License
Classifier: Operating System :: MacOS :: MacOS X
Classifier: Operating System :: Microsoft :: Windows
Classifier: Operating System :: POSIX
Classifier: Programming Language :: Python :: 3
Classifier: Programming Language :: Python :: 3.8
Classifier: Programming Language :: Python :: 3.9
Classifier: Programming Language :: Python :: 3.10
Classifier: Programming Language :: Python :: 3.11
Classifier: Programming Language :: Python :: 3.12
Classifier: Programming Language :: Python :: Implementation :: CPython
Classifier: Programming Language :: Python :: Implementation :: PyPy
Classifier: Topic :: Database
Requires-Python: >=3.8
Requires-Dist: boto3
Requires-Dist: botocore
Provides-Extra: test
Requires-Dist: dnspython>=2.6.1; extra == 'test'
Requires-Dist: pymongo; extra == 'test'
Requires-Dist: pytest; extra == 'test'
